mrprince/__init__.py
mrprince/main.py
mrprince-0.1.0.dist-info/LICENSE
mrprince-0.1.0.dist-info/METADATA
mrprince-0.1.0.dist-info/WHEEL
mrprince-0.1.0.dist-info/entry_points.txt
mrprince-0.1.0.dist-info/top_level.txt
mrprince-0.1.0.dist-info/RECORD
